{
  "auth": {
    "devhome76afbd00": {
      "service": "Cognito",
      "providerPlugin": "awscloudformation",
      "dependsOn": [],
      "customAuth": false
    }
  },
  "storage": {
    "devhome": {
      "service": "S3",
      "providerPlugin": "awscloudformation"
    }
  },
  "function": {
    "devhomes3geturl": {
      "build": true,
      "providerPlugin": "awscloudformation",
      "service": "Lambda",
      "dependsOn": [
        {
          "category": "storage",
          "resourceName": "devhome",
          "attributes": [
            "BucketName"
          ]
        }
      ]
    }
  },
  "api": {
    "devhomeapi": {
      "service": "API Gateway",
      "providerPlugin": "awscloudformation",
      "dependsOn": [
        {
          "category": "function",
          "resourceName": "devhomes3geturl",
          "attributes": [
            "Name",
            "Arn"
          ]
        }
      ]
    }
  }
}